infi.docopt_completion-0.2.9-py2.7-nspkg.pth
infi/docopt_completion/__init__.py
infi/docopt_completion/__version__.py
infi/docopt_completion/bash.py
infi/docopt_completion/common.py
infi/docopt_completion/docopt_completion.py
infi/docopt_completion/zsh.py
infi.docopt_completion-0.2.9.dist-info/LICENSE
infi.docopt_completion-0.2.9.dist-info/METADATA
infi.docopt_completion-0.2.9.dist-info/WHEEL
infi.docopt_completion-0.2.9.dist-info/entry_points.txt
infi.docopt_completion-0.2.9.dist-info/namespace_packages.txt
infi.docopt_completion-0.2.9.dist-info/top_level.txt
infi.docopt_completion-0.2.9.dist-info/RECORD
